nimbusml/__init__.py
nimbusml/__main__.py
nimbusml/base_predictor.py
nimbusml/base_transform.py
nimbusml/loss.py
nimbusml/pipeline.py
nimbusml/cluster/__init__.py
nimbusml/cluster/kmeansplusplus.py
nimbusml/datasets/__init__.py
nimbusml/datasets/datasets.py
nimbusml/datasets/image.py
nimbusml/datasets/baseline/__init__.py
nimbusml/datasets/baseline/featurizeImage_alexnet_output.csv
nimbusml/datasets/baseline/featurizeImage_resnet101_output.csv
nimbusml/datasets/baseline/featurizeImage_resnet18_output.csv
nimbusml/datasets/baseline/featurizeImage_resnet50_output.csv
nimbusml/datasets/data/__init__.py
nimbusml/datasets/data/test-100.uciadult.sample.csv
nimbusml/datasets/data/test-msltr.sample.csv
nimbusml/datasets/data/test-ticketchoice.csv
nimbusml/datasets/data/test-twitter.gen-sample.tsv
nimbusml/datasets/data/test.wikipedia.sample.tsv
nimbusml/datasets/data/test_fs.csv
nimbusml/datasets/data/timeseries.csv
nimbusml/datasets/data/topics.csv
nimbusml/datasets/data/train-250.wikipedia.sample.tsv
nimbusml/datasets/data/train-500.uciadult.sample.csv
nimbusml/datasets/data/train-msltr.sample.csv
nimbusml/datasets/data/train-ticketchoice.csv
nimbusml/datasets/data/train-twitter.gen-sample.tsv
nimbusml/datasets/data/train_fs.csv
nimbusml/datasets/data/gplv2/airquality.csv
nimbusml/datasets/data/gplv2/infert.csv
nimbusml/datasets/images/Microsoftlogo.png
nimbusml/datasets/images/RevolutionAnalyticslogo.png
nimbusml/datasets/images/__init__.py
nimbusml/decomposition/__init__.py
nimbusml/decomposition/factorizationmachinebinaryclassifier.py
nimbusml/decomposition/pcaanomalydetector.py
nimbusml/decomposition/pcatransformer.py
nimbusml/ensemble/__init__.py
nimbusml/ensemble/ensembleclassifier.py
nimbusml/ensemble/ensembleregressor.py
nimbusml/ensemble/fastforestbinaryclassifier.py
nimbusml/ensemble/fastforestregressor.py
nimbusml/ensemble/fasttreesbinaryclassifier.py
nimbusml/ensemble/fasttreesregressor.py
nimbusml/ensemble/fasttreestweedieregressor.py
nimbusml-1.8.0.dist-info/METADATA
nimbusml-1.8.0.dist-info/WHEEL
nimbusml-1.8.0.dist-info/top_level.txt
nimbusml-1.8.0.dist-info/RECORD
