Metadata-Version: 2.1
Name: nimbusml
Version: 1.8.0
Summary: NimbusML
Home-page: https://docs.microsoft.com/en-us/nimbusml
Author: Microsoft
Author-email: nimbusml@microsoft.com
License: All rights reserved
Keywords: microsoft ml ML.NET machine learning nimbusml
Platform: UNKNOWN
Classifier: Development Status :: 3 - Alpha
Classifier: Intended Audience :: Developers
Classifier: Programming Language :: Python :: 2.7
Classifier: Programming Language :: Python :: 3.5
Classifier: Programming Language :: Python :: 3.6
Classifier: Programming Language :: Python :: 3.7
Requires-Python: >3.5.*, <3.9.*
Requires-Dist: numpy (>=1.14.0)
Requires-Dist: pandas (>=0.22)
Requires-Dist: scipy (>=0.18)
Requires-Dist: scikit-learn (>0.19.0)
Requires-Dist: dotnetcore2 (>=2.1.2)
Provides-Extra: dprep
Requires-Dist: azureml-dataprep (>=1.1.33) ; extra == 'dprep'
Provides-Extra: tests
Requires-Dist: nose (>=1.3) ; extra == 'tests'
Requires-Dist: pytest (>=4.4.0) ; extra == 'tests'
Requires-Dist: graphviz ; extra == 'tests'
Requires-Dist: imageio ; extra == 'tests'
Requires-Dist: onnxruntime ; extra == 'tests'
Provides-Extra: utils
Requires-Dist: graphviz ; extra == 'utils'
Requires-Dist: imageio ; extra == 'utils'
